digitales_2/Tarea_3/estructurales/maquina_estados.v
// File: maquina_estados.v
// Descripción conductual 100% Verilog-2001 para síntesis

module maquina_estados (
    input         CLK,
    input         RESET,              // reset activo bajo
    input         tarjeta_received,
    input  [15:0] pin_correcto,
    input  [3:0]  digito,
    input         digito_stb,
    input         tipo_trans,         // 0=depósito, 1=retiro
    input  [31:0] monto,
    input         monto_stb,
    input  [63:0] balance_inicial,

    output reg [63:0] balance_actualizado,
    output reg        balance_stb,
    output reg        entregar_dinero,
    output reg        fondos_insuficientes,
    output reg        pin_incorrecto,
    output reg        advertencia,
    output reg        bloqueo
);

    // Codificación de estados
    parameter S_IDLE           = 4'd0;
    parameter S_PIN_ENTRY      = 4'd1;
    parameter S_CHECK_PIN      = 4'd2;
    parameter S_INCORRECT      = 4'd3;
    parameter S_LOCKED         = 4'd4;
    parameter S_TRANS_TYPE     = 4'd5;
    parameter S_DEPOSIT        = 4'd6;
    parameter S_WITHDRAW_CHECK = 4'd7;
    parameter S_WITHDRAW       = 4'd8;
    parameter S_INSUFFICIENT   = 4'd9;

    reg [3:0]  state, next_state;
    reg [1:0]  attempts;
    reg [1:0]  pin_idx;
    reg [15:0] pin_buffer;
    reg [63:0] balance_reg;

    // Registro de estado y operaciones secuenciales
    always @(posedge CLK or negedge RESET) begin
        if (!RESET) begin
            state        <= S_IDLE;
            attempts     <= 2'b00;
            pin_idx      <= 2'b00;
            pin_buffer   <= 16'b0;
            balance_reg  <= 64'b0;
        end else begin
            state <= next_state;

            // Captura dígitos de PIN
            if (state == S_PIN_ENTRY && digito_stb) begin
                pin_buffer <= { pin_buffer[11:0], digito };
                pin_idx    <= pin_idx + 1;
            end

            // Contar intentos y latch de balance
            if (state == S_CHECK_PIN) begin
                if (pin_buffer != pin_correcto)
                    attempts <= attempts + 1;
                else
                    balance_reg <= balance_inicial;
            end

            // Actualizar balance según transacción
            if (state == S_DEPOSIT)
                balance_reg <= balance_reg + monto;
            if (state == S_WITHDRAW)
                balance_reg <= balance_reg - monto;
        end
    end

    // Lógica combinacional de siguiente estado y salidas
    always @(*) begin
        // Defaults
        next_state           = state;
        pin_incorrecto       = 1'b0;
        advertencia          = 1'b0;
        bloqueo              = 1'b0;
        balance_stb          = 1'b0;
        entregar_dinero      = 1'b0;
        fondos_insuficientes = 1'b0;
        balance_actualizado  = balance_reg;

        case (state)
            S_IDLE: begin
                if (tarjeta_received)
                    next_state = S_PIN_ENTRY;
            end

            S_PIN_ENTRY: begin
                if (digito_stb && pin_idx == 2'd3)
                    next_state = S_CHECK_PIN;
            end

            S_CHECK_PIN: begin
                if (pin_buffer == pin_correcto)
                    next_state = S_TRANS_TYPE;
                else if (attempts == 2'd2)
                    next_state = S_LOCKED;
                else
                    next_state = S_INCORRECT;
            end

            S_INCORRECT: begin
                pin_incorrecto = 1'b1;
                if (attempts == 2'd2)
                    advertencia = 1'b1;
                next_state = S_PIN_ENTRY;
            end

            S_LOCKED: begin
                bloqueo   = 1'b1;
                next_state = S_LOCKED;
            end

            S_TRANS_TYPE: begin
                if (monto_stb)
                    next_state = (tipo_trans == 1'b0) ? S_DEPOSIT : S_WITHDRAW_CHECK;
            end

            S_DEPOSIT: begin
                balance_stb = 1'b1;
                next_state  = S_IDLE;
            end

            S_WITHDRAW_CHECK: begin
                if (monto <= balance_reg)
                    next_state = S_WITHDRAW;
                else
                    next_state = S_INSUFFICIENT;
            end

            S_WITHDRAW: begin
                balance_stb     = 1'b1;
                entregar_dinero = 1'b1;
                next_state      = S_IDLE;
            end

            S_INSUFFICIENT: begin
                fondos_insuficientes = 1'b1;
                next_state           = S_IDLE;
            end

            default: next_state = S_IDLE;
        endcase
    end

endmodule

digitales_2/Tarea_3/estructurales/tester.v
// File: tester.v
// Módulo que genera estímulos para un balance inicial de 100 y retiro de 50

module tester (
    output reg        CLK,
    output reg        RESET,
    output reg        tarjeta_received,
    output reg [15:0] pin_correcto,
    output reg [3:0]  digito,
    output reg        digito_stb,
    output reg        tipo_trans,
    output reg [31:0] monto,
    output reg        monto_stb,
    output reg [63:0] balance_inicial
);
    // Reloj de 10 ns
    initial CLK = 1'b0;
    always #5 CLK = ~CLK;

    initial begin
        // Inicialización de señales
        RESET            = 1'b0;
        tarjeta_received = 1'b0;
        pin_correcto     = 16'h1234;   // PIN de ejemplo: 1,2,3,4
        digito           = 4'd0;
        digito_stb       = 1'b0;
        tipo_trans       = 1'b0;
        monto            = 32'd0;
        monto_stb        = 1'b0;
        balance_inicial  = 64'd100;    // Balance inicial = 100

        // Generar reset activo bajo durante 20 ns
        #20 RESET = 1'b1;

        // -- Caso 1: dos intentos de PIN erróneos --
        // Primer intento: 5,5,5,5
        #20 tarjeta_received = 1'b1;
        repeat (4) begin
            @(posedge CLK);
            digito     = 4'd5;
            digito_stb = 1'b1;
            @(posedge CLK);
            digito_stb = 1'b0;
        end
        @(posedge CLK) tarjeta_received = 1'b0;
        #20;

        // Segundo intento: 6,6,6,6
        @(posedge CLK) tarjeta_received = 1'b1;
        repeat (4) begin
            @(posedge CLK);
            digito     = 4'd6;
            digito_stb = 1'b1;
            @(posedge CLK);
            digito_stb = 1'b0;
        end
        @(posedge CLK) tarjeta_received = 1'b0;
        #20;

        // -- Tercer intento CORRECTO: 1,2,3,4 --
        @(posedge CLK) tarjeta_received = 1'b1;
        // Dígito 1
        @(posedge CLK);
          digito     = 4'd1; digito_stb = 1'b1;
        @(posedge CLK); digito_stb = 1'b0;
        // Dígito 2
        @(posedge CLK);
          digito     = 4'd2; digito_stb = 1'b1;
        @(posedge CLK); digito_stb = 1'b0;
        // Dígito 3
        @(posedge CLK);
          digito     = 4'd3; digito_stb = 1'b1;
        @(posedge CLK); digito_stb = 1'b0;
        // Dígito 4
        @(posedge CLK);
          digito     = 4'd4; digito_stb = 1'b1;
        @(posedge CLK); digito_stb = 1'b0;

        @(posedge CLK) tarjeta_received = 1'b0;
        #20;

        // -- Ahora: RETIRO de 50 --
        tipo_trans = 1'b0;    // 1 = retiro
        monto      = 32'd50;  // monto a retirar = 50
        @(posedge CLK); monto_stb = 1'b1;
        @(posedge CLK); monto_stb = 1'b0;

        // Esperar unos ciclos y terminar
        #100 $finish;
    end
endmodule

digitales_2/Tarea_3/estructurales/testbench.v
// File: testbench.v
// Instanciación del DUT y del probador, y VCD para GTKWave

`timescale 1ns/1ps

module testbench;
    // Señales compartidas
    wire        CLK, RESET, tarjeta_received;
    wire [15:0] pin_correcto;
    wire [3:0]  digito;
    wire        digito_stb, tipo_trans, monto_stb;
    wire [31:0] monto;
    wire [63:0] balance_inicial;

    wire [63:0] balance_actualizado;
    wire        balance_stb, entregar_dinero;
    wire        fondos_insuficientes, pin_incorrecto;
    wire        advertencia, bloqueo;

    // Probador
    tester TB (
        .CLK(CLK),
        .RESET(RESET),
        .tarjeta_received(tarjeta_received),
        .pin_correcto(pin_correcto),
        .digito(digito),
        .digito_stb(digito_stb),
        .tipo_trans(tipo_trans),
        .monto(monto),
        .monto_stb(monto_stb),
        .balance_inicial(balance_inicial)
    );

    // DUT
    maquina_estados DUT (
        .CLK(CLK),
        .RESET(RESET),
        .tarjeta_received(tarjeta_received),
        .pin_correcto(pin_correcto),
        .digito(digito),
        .digito_stb(digito_stb),
        .tipo_trans(tipo_trans),
        .monto(monto),
        .monto_stb(monto_stb),
        .balance_inicial(balance_inicial),
        .balance_actualizado(balance_actualizado),
        .balance_stb(balance_stb),
        .entregar_dinero(entregar_dinero),
        .fondos_insuficientes(fondos_insuficientes),
        .pin_incorrecto(pin_incorrecto),
        .advertencia(advertencia),
        .bloqueo(bloqueo)
    );

    initial begin
        $dumpfile("maquina_estados.vcd");
        $dumpvars(0, testbench);
    end
endmodule

digitales_2/Tarea_3/estructurales/maquina_estados.vcd
$date
	Sun May  4 17:13:00 2025
$end
$version
	Icarus Verilog
$end
$timescale
	1ps
$end
$scope module testbench $end
$var wire 1 ! tipo_trans $end
$var wire 1 " tarjeta_received $end
$var wire 1 # pin_incorrecto $end
$var wire 16 $ pin_correcto [15:0] $end
$var wire 1 % monto_stb $end
$var wire 32 & monto [31:0] $end
$var wire 1 ' fondos_insuficientes $end
$var wire 1 ( entregar_dinero $end
$var wire 1 ) digito_stb $end
$var wire 4 * digito [3:0] $end
$var wire 1 + bloqueo $end
$var wire 1 , balance_stb $end
$var wire 64 - balance_inicial [63:0] $end
$var wire 64 . balance_actualizado [63:0] $end
$var wire 1 / advertencia $end
$var wire 1 0 RESET $end
$var wire 1 1 CLK $end
$scope module DUT $end
$var wire 1 ! tipo_trans $end
$var wire 1 " tarjeta_received $end
$var wire 16 2 pin_correcto [15:0] $end
$var wire 1 % monto_stb $end
$var wire 32 3 monto [31:0] $end
$var wire 1 ) digito_stb $end
$var wire 4 4 digito [3:0] $end
$var wire 64 5 balance_inicial [63:0] $end
$var wire 1 0 RESET $end
$var wire 1 1 CLK $end
$var parameter 4 6 S_CHECK_PIN $end
$var parameter 4 7 S_DEPOSIT $end
$var parameter 4 8 S_IDLE $end
$var parameter 4 9 S_INCORRECT $end
$var parameter 4 : S_INSUFFICIENT $end
$var parameter 4 ; S_LOCKED $end
$var parameter 4 < S_PIN_ENTRY $end
$var parameter 4 = S_TRANS_TYPE $end
$var parameter 4 > S_WITHDRAW $end
$var parameter 4 ? S_WITHDRAW_CHECK $end
$var reg 1 / advertencia $end
$var reg 2 @ attempts [1:0] $end
$var reg 64 A balance_actualizado [63:0] $end
$var reg 64 B balance_reg [63:0] $end
$var reg 1 , balance_stb $end
$var reg 1 + bloqueo $end
$var reg 1 ( entregar_dinero $end
$var reg 1 ' fondos_insuficientes $end
$var reg 4 C next_state [3:0] $end
$var reg 16 D pin_buffer [15:0] $end
$var reg 2 E pin_idx [1:0] $end
$var reg 1 # pin_incorrecto $end
$var reg 4 F state [3:0] $end
$upscope $end
$scope module TB $end
$var reg 1 1 CLK $end
$var reg 1 0 RESET $end
$var reg 64 G balance_inicial [63:0] $end
$var reg 4 H digito [3:0] $end
$var reg 1 ) digito_stb $end
$var reg 32 I monto [31:0] $end
$var reg 1 % monto_stb $end
$var reg 16 J pin_correcto [15:0] $end
$var reg 1 " tarjeta_received $end
$var reg 1 ! tipo_trans $end
$upscope $end
$upscope $end
$enddefinitions $end
$comment Show the parameter values. $end
$dumpall
b111 ?
b1000 >
b101 =
b1 <
b100 ;
b1001 :
b11 9
b0 8
b110 7
b10 6
$end
#0
$dumpvars
b1001000110100 J
b0 I
b0 H
b1100100 G
bx F
bx E
bx D
b0 C
bx B
bx A
bx @
b1100100 5
b0 4
b0 3
b1001000110100 2
01
00
0/
bx .
b1100100 -
0,
0+
b0 *
0)
0(
0'
b0 &
0%
b1001000110100 $
0#
0"
0!
$end
#5000
b0 .
b0 A
b0 B
b0 D
b0 E
b0 @
b0 F
11
#10000
01
#15000
11
#20000
01
10
#25000
11
#30000
01
#35000
11
#40000
b1 C
01
1"
#45000
b1 F
b1 C
1)
b101 *
b101 4
b101 H
11
#50000
01
#55000
0)
11
#60000
01
#65000
b1 E
b101 D
1)
11
#70000
01
#75000
0)
11
#80000
01
#85000
b10 E
b1010101 D
1)
11
#90000
01
#95000
0)
11
#100000
01
#105000
b10 C
b11 E
b10101010101 D
1)
11
#110000
01
#115000
b10 F
b11 C
0)
11
#120000
01
#125000
1#
b1 @
b11 F
b1 C
0"
11
#130000
01
#135000
0#
b1 F
11
#140000
01
#145000
1"
11
#150000
01
#155000
b0 E
b101010101010110 D
b1 C
1)
b110 *
b110 4
b110 H
11
#160000
01
#165000
0)
11
#170000
01
#175000
b1 E
b101010101100110 D
1)
11
#180000
01
#185000
0)
11
#190000
01
#195000
b10 E
b101011001100110 D
1)
11
#200000
01
#205000
0)
11
#210000
01
#215000
b10 C
b11 E
b110011001100110 D
1)
11
#220000
01
#225000
b10 F
b11 C
0)
11
#230000
01
#235000
1/
1#
b10 @
b11 F
b1 C
0"
11
#240000
01
#245000
0/
0#
b1 F
11
#250000
01
#255000
1"
11
#260000
01
#265000
b0 E
b110011001100001 D
b1 C
1)
b1 *
b1 4
b1 H
11
#270000
01
#275000
0)
11
#280000
01
#285000
b1 E
b110011000010010 D
1)
b10 *
b10 4
b10 H
11
#290000
01
#295000
0)
11
#300000
01
#305000
b10 E
b110000100100011 D
1)
b11 *
b11 4
b11 H
11
#310000
01
#315000
0)
11
#320000
01
#325000
b10 C
b11 E
b1001000110100 D
1)
b100 *
b100 4
b100 H
11
#330000
01
#335000
b10 F
b101 C
0)
11
#340000
01
#345000
b1100100 .
b1100100 A
b1100100 B
b101 F
b101 C
0"
11
#350000
01
#355000
11
#360000
01
#365000
b110 C
1%
11
b110010 &
b110010 3
b110010 I
#370000
01
#375000
1,
b110 F
b0 C
0%
11
#380000
01
#385000
b10010110 .
b10010110 A
0,
b10010110 B
b0 F
11
